
{"cartoes": [{
    "id": "12034",
    "nome": "Felipe M Silva",
    "data": "07/30",
    "numero": "1234 3245 .... ....",
    "bandeira": "master"
},
{
    "id": "12031",
    "nome": "Elder Alcantara",
    "data": "02/31",
    "numero": "2345 3245 .... ....",
    "bandeira": "visa"
},
{
    "id": "12031",
    "nome": "Aline Borges",
    "data": "02/31",
    "numero": "3456 3245 .... ....",
    "bandeira": "visa"
},
{
    "id": "12031",
    "nome": "Danilo Coelho",
    "data": "02/31",
    "numero": "4567 3245 .... ....",
    "bandeira": "visa"
}
]
}
